biopython/__init__.py
biopython/tools/__init__.py
biopythonings-0.1.dist-info/METADATA
biopythonings-0.1.dist-info/WHEEL
biopythonings-0.1.dist-info/top_level.txt
biopythonings-0.1.dist-info/RECORD
