Metadata-Version: 2.4
Name: biopythonings
Version: 0.1
Summary: All of meow's custom bioinformatics tools
Author: meow
Classifier: Programming Language :: Python :: 3
Classifier: License :: OSI Approved :: MIT License
Dynamic: author
Dynamic: classifier
Dynamic: description
Dynamic: description-content-type
Dynamic: summary
